{
  "RELOH": {
    "tipo_venda": "1",
    "desc_tipo_venda": "1 - A VISTA",
    "valor_entrada": "0,00",
    "plano": "",
    "status_pedido": "Em Elaboração",
    "statusAtualizadoAposSalvarPedido": "Em Elaboracao",
    "statusAposFechamentoTotalPedido": "Ag. Recebimento",
    "msg_success_ao_finalizar": "Status: 30 - Ag. Recebimento",
    "ind_analise_credito": false,
    "btn_confirme_analise": false,
    "produtos": [
      {
        "cod_departamento": "",
        "cod_grupo_produto": "",
        "desc_departamento": "",
        "desc_grupo_produto": "",
        "cod_sub_grupo_produto": "",
        "desc_sub_grupo_produto": "",
        "cod_nro_produto": "215275",
        "cod_cor_produto": "0",
        "cod_tipo_voltagem": "B",
        "ind_entrega_produto": "SIM",
        "descricao": "TV PANASONIC 32 TC-32A400B LED HD",
        "ind_entrega_atualizado": "SIM",
        "qtd": null,
        "tabela": null,
        "desc_tabela": null,
        "valor_unitario": null,
        "ind_editar_produto": false,
        "empenho": {
          "local_empenho": 1,
          "desc_local_empenho": "DEPOSITO",
          "opcao_entrega": 6,
          "desc_opcao_entrega": "AGENDADA",
          "entrega": true,
          "data_entrega_cliente_erro": null,
          "data_entrega_cliente": "18/02/2016",
          "ind_data_sistema": null,
          "data_retencao": null,
          "turno": null,
          "desc_turno": "TARDE",
          "desc_turno_erro": null,
          "ind_validacao_data_agendamento": null,
          "nro_loja_empenho": null,
          "ind_valid_regra_cad_endereco": false,
          "empenha_sem_emitir_mensagem": true
        },
        "promocao": {
          "ind_promocao_ativa": false,
          "ind_sel_promo": false
        }
      }
    ],
    "planilhas": [
      {
        "tipo": "V",
        "forma_pagamento": "DINHEIRO",
        "cod_forma_pagamento": "1",
        "valor": "3.180,80",
        "ind_inserir_valor": false,
        "ind_gerar_financiamento": null,
        "documento": null
      }
    ],
    "servicos": [
      {
        "cod_servico": "163594",
        "descricao": "SEG CAMINHAO DA SORTE.",
        "ind_ativo": false
      },
      {
        "cod_servico": "104141",
        "descricao": "FRETE",
        "ind_ativo": true
      }
    ],
    "garantias": [
      {
        "desc_produto": "TV PANASONIC 32 TC-32A400B LED HD",
        "cod_produto": "215275",
        "cor": "0",
        "voltagem": "B",
        "garantias": [
          {
            "cod_servico": "140358",
            "nome_servico": "INSTALAÇÃO_DE_TV",
            "produto": "215275.0.B",
            "ind_add": false,
            "ind_existe": true
          },
          {
            "cod_servico": "144658",
            "nome_servico": "GARANTIA MAIOR TV LCD - 2 ANOS.",
            "produto": "215275.0.B",
            "ind_add": false,
            "ind_existe": true,
            "ind_validacao": false,
            "usuario": "291",
        	"senha": "1"
          },
          {
            "cod_servico": "215914",
            "nome_servico": "AJUSTE DE PREÇO (LINHA VIDEO)",
            "produto": "215275.0.B",
            "ind_add": false,
            "ind_existe": true,
            "ind_validacao": false
          }
        ]
      }
    ]
  }
}